MANIFEST.in
README.txt
reflector.py
setup.py
reflector.egg-info/PKG-INFO
reflector.egg-info/SOURCES.txt
reflector.egg-info/dependency_links.txt
reflector.egg-info/entry_points.txt
reflector.egg-info/top_level.txt