Metadata-Version: 1.0
Name: reflector
Version: 0.1
Summary: TCP connection reflector
Home-page: http://github.com/sorenh/reflector
Author: Soren Hansen
Author-email: Soren.Hansen@ril.com
License: Apache 2.0
Keywords: tcp network monitoring
Platform: UNKNOWN
